MANIFEST.in
README.rst
setup.py
perseus_nemo_ui/__init__.py
perseus_nemo_ui.egg-info/PKG-INFO
perseus_nemo_ui.egg-info/SOURCES.txt
perseus_nemo_ui.egg-info/dependency_links.txt
perseus_nemo_ui.egg-info/not-zip-safe
perseus_nemo_ui.egg-info/requires.txt
perseus_nemo_ui.egg-info/top_level.txt
perseus_nemo_ui/data/assets/css/theme-ext.css
perseus_nemo_ui/data/assets/images/rev_running_man.png
perseus_nemo_ui/data/assets/static/xslt/edition.xsl
perseus_nemo_ui/data/assets/static/xslt/epidoc.css
perseus_nemo_ui/data/assets/static/xslt/epidocShort.xsl
perseus_nemo_ui/data/assets/static/xslt/facsimile.xsl
perseus_nemo_ui/data/assets/static/xslt/licence.md
perseus_nemo_ui/data/assets/static/xslt/teiHeader.xsl
perseus_nemo_ui/data/assets/static/xslt/teig.xsl
perseus_nemo_ui/data/assets/static/xslt/text.xsl
perseus_nemo_ui/data/assets/static/xslt/translation.xsl
perseus_nemo_ui/data/templates/index.html
perseus_nemo_ui/data/templates/menu.html
perseus_nemo_ui/data/templates/passage_footer.html