Metadata-Version: 1.0
Name: perseus-nemo-ui
Version: 0.0.23
Summary: Plugin for Perseus UI for Nemo
Home-page: https://github.com/PerseusDL/perseus_nemo_ui
Author: Bridget Almas
Author-email: balmas@gmail.com
License: GNU GPL
Platform: UNKNOWN
